{
  "schemaVersion": 1,
  "specKey": "13092",
  "rowCount": 20,
  "generatedAt": "2026-06-09T02:27:27.040Z",
  "source": "../Piping_class_master.json",
  "rows": [
    {
      "Piping Class": "13092",
      "Size": "0.5",
      "SCH": "40S",
      "Wall thickness": "2.7686000000000002",
      "Material_Name": "ASTM A312-TP304",
      "PMSMat_Categories": "Stainl steel AISI 304 LT",
      "PMSMat_Cat": "SS",
      "Rating": "150",
      "Corrosion": "0",
      "convertedBore": 15,
      "_sourceRowIndex": 2201
    },
    {
      "Piping Class": "13092",
      "Size": "0.75",
      "SCH": "40S",
      "Wall thickness": "2.8702000000000001",
      "Material_Name": "ASTM A312-TP304",
      "PMSMat_Categories": "Stainl steel AISI 304 LT",
      "PMSMat_Cat": "SS",
      "Rating": "150",
      "Corrosion": "0",
      "convertedBore": 20,
      "_sourceRowIndex": 2202
    },
    {
      "Piping Class": "13092",
      "Size": "1",
      "SCH": "10S",
      "Wall thickness": "2.77",
      "Material_Name": "ASTM A312-TP304",
      "PMSMat_Categories": "Stainl steel AISI 304 LT",
      "PMSMat_Cat": "SS",
      "Rating": "150",
      "Corrosion": "0",
      "convertedBore": 25,
      "_sourceRowIndex": 2203
    },
    {
      "Piping Class": "13092",
      "Size": "1.5",
      "SCH": "10S",
      "Wall thickness": "2.77",
      "Material_Name": "ASTM A312-TP304",
      "PMSMat_Categories": "Stainl steel AISI 304 LT",
      "PMSMat_Cat": "SS",
      "Rating": "150",
      "Corrosion": "0",
      "convertedBore": 40,
      "_sourceRowIndex": 2204
    },
    {
      "Piping Class": "13092",
      "Size": "2",
      "SCH": "10S",
      "Wall thickness": "2.77",
      "Material_Name": "ASTM A312-TP304",
      "PMSMat_Categories": "Stainl steel AISI 304 LT",
      "PMSMat_Cat": "SS",
      "Rating": "150",
      "Corrosion": "0",
      "convertedBore": 50,
      "_sourceRowIndex": 2205
    },
    {
      "Piping Class": "13092",
      "Size": "3",
      "SCH": "10S",
      "Wall thickness": "3.048",
      "Material_Name": "ASTM A312-TP304",
      "PMSMat_Categories": "Stainl steel AISI 304 LT",
      "PMSMat_Cat": "SS",
      "Rating": "150",
      "Corrosion": "0",
      "convertedBore": 80,
      "_sourceRowIndex": 2206
    },
    {
      "Piping Class": "13092",
      "Size": "4",
      "SCH": "10S",
      "Wall thickness": "3.048",
      "Material_Name": "ASTM A312-TP304",
      "PMSMat_Categories": "Stainl steel AISI 304 LT",
      "PMSMat_Cat": "SS",
      "Rating": "150",
      "Corrosion": "0",
      "convertedBore": 100,
      "_sourceRowIndex": 2207
    },
    {
      "Piping Class": "13092",
      "Size": "6",
      "SCH": "10S",
      "Wall thickness": "3.4036",
      "Material_Name": "ASTM A312-TP304",
      "PMSMat_Categories": "Stainl steel AISI 304 LT",
      "PMSMat_Cat": "SS",
      "Rating": "150",
      "Corrosion": "0",
      "convertedBore": 150,
      "_sourceRowIndex": 2208
    },
    {
      "Piping Class": "13092",
      "Size": "8",
      "SCH": "10S",
      "Wall thickness": "3.7591999999999999",
      "Material_Name": "ASTM A312-TP304",
      "PMSMat_Categories": "Stainl steel AISI 304 LT",
      "PMSMat_Cat": "SS",
      "Rating": "150",
      "Corrosion": "0",
      "convertedBore": 200,
      "_sourceRowIndex": 2209
    },
    {
      "Piping Class": "13092",
      "Size": "10",
      "SCH": "10S",
      "Wall thickness": "4.1909999999999998",
      "Material_Name": "ASTM A312-TP304",
      "PMSMat_Categories": "Stainl steel AISI 304 LT",
      "PMSMat_Cat": "SS",
      "Rating": "150",
      "Corrosion": "0",
      "convertedBore": 250,
      "_sourceRowIndex": 2210
    },
    {
      "Piping Class": "13092",
      "Size": "12",
      "SCH": "10S",
      "Wall thickness": "4.5720000000000001",
      "Material_Name": "ASTM A312-TP304",
      "PMSMat_Categories": "Stainl steel AISI 304 LT",
      "PMSMat_Cat": "SS",
      "Rating": "150",
      "Corrosion": "0",
      "convertedBore": 300,
      "_sourceRowIndex": 2211
    },
    {
      "Piping Class": "13092",
      "Size": "14",
      "SCH": "10S",
      "Wall thickness": "4.7751999999999999",
      "Material_Name": "ASTM A358-304",
      "PMSMat_Categories": "Stainl steel AISI 304 LT",
      "PMSMat_Cat": "SS",
      "Rating": "150",
      "Corrosion": "0",
      "convertedBore": 350,
      "_sourceRowIndex": 2212
    },
    {
      "Piping Class": "13092",
      "Size": "16",
      "SCH": "10S",
      "Wall thickness": "4.7751999999999999",
      "Material_Name": "ASTM A358-304",
      "PMSMat_Categories": "Stainl steel AISI 304 LT",
      "PMSMat_Cat": "SS",
      "Rating": "150",
      "Corrosion": "0",
      "convertedBore": 400,
      "_sourceRowIndex": 2213
    },
    {
      "Piping Class": "13092",
      "Size": "18",
      "SCH": "10S",
      "Wall thickness": "4.7751999999999999",
      "Material_Name": "ASTM A358-304",
      "PMSMat_Categories": "Stainl steel AISI 304 LT",
      "PMSMat_Cat": "SS",
      "Rating": "150",
      "Corrosion": "0",
      "convertedBore": 450,
      "_sourceRowIndex": 2214
    },
    {
      "Piping Class": "13092",
      "Size": "20",
      "SCH": "10S",
      "Wall thickness": "5.5372000000000003",
      "Material_Name": "ASTM A358-304",
      "PMSMat_Categories": "Stainl steel AISI 304 LT",
      "PMSMat_Cat": "SS",
      "Rating": "150",
      "Corrosion": "0",
      "convertedBore": 500,
      "_sourceRowIndex": 2215
    },
    {
      "Piping Class": "13092",
      "Size": "24",
      "SCH": "10S",
      "Wall thickness": "6.35",
      "Material_Name": "ASTM A358-304",
      "PMSMat_Categories": "Stainl steel AISI 304 LT",
      "PMSMat_Cat": "SS",
      "Rating": "150",
      "Corrosion": "0",
      "convertedBore": 600,
      "_sourceRowIndex": 2216
    },
    {
      "Piping Class": "13092",
      "Size": "30",
      "SCH": "10S",
      "Wall thickness": "7.9248000000000003",
      "Material_Name": "ASTM A358-304",
      "PMSMat_Categories": "Stainl steel AISI 304 LT",
      "PMSMat_Cat": "SS",
      "Rating": "150",
      "Corrosion": "0",
      "convertedBore": 750,
      "_sourceRowIndex": 2217
    },
    {
      "Piping Class": "13092",
      "Size": "36",
      "SCH": "10",
      "Wall thickness": "7.9248000000000003",
      "Material_Name": "ASTM A358-304",
      "PMSMat_Categories": "Stainl steel AISI 304 LT",
      "PMSMat_Cat": "SS",
      "Rating": "150",
      "Corrosion": "0",
      "convertedBore": 900,
      "_sourceRowIndex": 2218
    },
    {
      "Piping Class": "13092",
      "Size": "42",
      "SCH": "8.7",
      "Wall thickness": "8.6999999999999993",
      "Material_Name": "ASTM A358-304",
      "PMSMat_Categories": "Stainl steel AISI 304 LT",
      "PMSMat_Cat": "SS",
      "Rating": "150",
      "Corrosion": "0",
      "convertedBore": 1050,
      "_sourceRowIndex": 2219
    },
    {
      "Piping Class": "13092",
      "Size": "48",
      "SCH": "8.7",
      "Wall thickness": "8.6999999999999993",
      "Material_Name": "ASTM A358-304",
      "PMSMat_Categories": "Stainl steel AISI 304 LT",
      "PMSMat_Cat": "SS",
      "Rating": "150",
      "Corrosion": "0",
      "convertedBore": 1200,
      "_sourceRowIndex": 2220
    }
  ]
}
