{
  "schemaVersion": 1,
  "specKey": "251440",
  "rowCount": 11,
  "generatedAt": "2026-06-26T20:32:29.645Z",
  "source": "../Piping_class_master.json",
  "rows": [
    {
      "Piping Class": "251440",
      "Size": "0.5",
      "SCH": "XXS",
      "Wall thickness": "7.4676",
      "Material_Name": "ASTM A106-B",
      "PMSMat_Categories": "Carbon steel Sour",
      "PMSMat_Cat": "CS",
      "Rating": "2500",
      "Corrosion": "3",
      "convertedBore": 15,
      "_sourceRowIndex": 3760
    },
    {
      "Piping Class": "251440",
      "Size": "0.75",
      "SCH": "XXS",
      "Wall thickness": "7.8231999999999999",
      "Material_Name": "ASTM A106-B",
      "PMSMat_Categories": "Carbon steel Sour",
      "PMSMat_Cat": "CS",
      "Rating": "2500",
      "Corrosion": "3",
      "convertedBore": 20,
      "_sourceRowIndex": 3761
    },
    {
      "Piping Class": "251440",
      "Size": "1",
      "SCH": "XXS",
      "Wall thickness": "9.0931999999999995",
      "Material_Name": "ASTM A106-B",
      "PMSMat_Categories": "Carbon steel Sour",
      "PMSMat_Cat": "CS",
      "Rating": "2500",
      "Corrosion": "3",
      "convertedBore": 25,
      "_sourceRowIndex": 3762
    },
    {
      "Piping Class": "251440",
      "Size": "1.5",
      "SCH": "XXS",
      "Wall thickness": "10.16",
      "Material_Name": "ASTM A106-B",
      "PMSMat_Categories": "Carbon steel Sour",
      "PMSMat_Cat": "CS",
      "Rating": "2500",
      "Corrosion": "3",
      "convertedBore": 40,
      "_sourceRowIndex": 3763
    },
    {
      "Piping Class": "251440",
      "Size": "2",
      "SCH": "XXS",
      "Wall thickness": "11.074400000000001",
      "Material_Name": "ASTM A106-B",
      "PMSMat_Categories": "Carbon steel Sour",
      "PMSMat_Cat": "CS",
      "Rating": "2500",
      "Corrosion": "3",
      "convertedBore": 50,
      "_sourceRowIndex": 3764
    },
    {
      "Piping Class": "251440",
      "Size": "3",
      "SCH": "XXS",
      "Wall thickness": "15.24",
      "Material_Name": "ASTM A106-B",
      "PMSMat_Categories": "Carbon steel Sour",
      "PMSMat_Cat": "CS",
      "Rating": "2500",
      "Corrosion": "3",
      "convertedBore": 80,
      "_sourceRowIndex": 3765
    },
    {
      "Piping Class": "251440",
      "Size": "4",
      "SCH": "XXS",
      "Wall thickness": "17.119599999999998",
      "Material_Name": "ASTM A106-B",
      "PMSMat_Categories": "Carbon steel Sour",
      "PMSMat_Cat": "CS",
      "Rating": "2500",
      "Corrosion": "3",
      "convertedBore": 100,
      "_sourceRowIndex": 3766
    },
    {
      "Piping Class": "251440",
      "Size": "6",
      "SCH": "XXS",
      "Wall thickness": "21.945599999999999",
      "Material_Name": "ASTM A106-B",
      "PMSMat_Categories": "Carbon steel Sour",
      "PMSMat_Cat": "CS",
      "Rating": "2500",
      "Corrosion": "3",
      "convertedBore": 150,
      "_sourceRowIndex": 3767
    },
    {
      "Piping Class": "251440",
      "Size": "8",
      "SCH": "28.0",
      "Wall thickness": "28",
      "Material_Name": "ASTM A333-6",
      "PMSMat_Categories": "Carbon steel Sour",
      "PMSMat_Cat": "CS",
      "Rating": "2500",
      "Corrosion": "3",
      "convertedBore": 200,
      "_sourceRowIndex": 3768
    },
    {
      "Piping Class": "251440",
      "Size": "10",
      "SCH": "34.0",
      "Wall thickness": "34",
      "Material_Name": "ASTM A333-6",
      "PMSMat_Categories": "Carbon steel Sour",
      "PMSMat_Cat": "CS",
      "Rating": "2500",
      "Corrosion": "3",
      "convertedBore": 250,
      "_sourceRowIndex": 3769
    },
    {
      "Piping Class": "251440",
      "Size": "12",
      "SCH": "40.0",
      "Wall thickness": "40",
      "Material_Name": "ASTM A333-6",
      "PMSMat_Categories": "Carbon steel Sour",
      "PMSMat_Cat": "CS",
      "Rating": "2500",
      "Corrosion": "3",
      "convertedBore": 300,
      "_sourceRowIndex": 3770
    }
  ]
}
