{
  "schemaVersion": 1,
  "specKey": "91432",
  "rowCount": 16,
  "generatedAt": "2026-06-09T02:27:27.117Z",
  "source": "../Piping_class_master.json",
  "rows": [
    {
      "Piping Class": "91432",
      "Size": "0.5",
      "SCH": "160",
      "Wall thickness": "4.7751999999999999",
      "Material_Name": "ASTM A106-B",
      "PMSMat_Categories": "Carbon steel",
      "PMSMat_Cat": "CS",
      "Rating": "900",
      "Corrosion": "3",
      "convertedBore": 15,
      "_sourceRowIndex": 9770
    },
    {
      "Piping Class": "91432",
      "Size": "0.75",
      "SCH": "160",
      "Wall thickness": "5.5625999999999998",
      "Material_Name": "ASTM A106-B",
      "PMSMat_Categories": "Carbon steel",
      "PMSMat_Cat": "CS",
      "Rating": "900",
      "Corrosion": "3",
      "convertedBore": 20,
      "_sourceRowIndex": 9771
    },
    {
      "Piping Class": "91432",
      "Size": "1",
      "SCH": "160",
      "Wall thickness": "6.35",
      "Material_Name": "ASTM A106-B",
      "PMSMat_Categories": "Carbon steel",
      "PMSMat_Cat": "CS",
      "Rating": "900",
      "Corrosion": "3",
      "convertedBore": 25,
      "_sourceRowIndex": 9772
    },
    {
      "Piping Class": "91432",
      "Size": "1.5",
      "SCH": "160",
      "Wall thickness": "7.1374000000000004",
      "Material_Name": "ASTM A106-B",
      "PMSMat_Categories": "Carbon steel",
      "PMSMat_Cat": "CS",
      "Rating": "900",
      "Corrosion": "3",
      "convertedBore": 40,
      "_sourceRowIndex": 9773
    },
    {
      "Piping Class": "91432",
      "Size": "2",
      "SCH": "160",
      "Wall thickness": "8.7376000000000005",
      "Material_Name": "ASTM A106-B",
      "PMSMat_Categories": "Carbon steel",
      "PMSMat_Cat": "CS",
      "Rating": "900",
      "Corrosion": "3",
      "convertedBore": 50,
      "_sourceRowIndex": 9774
    },
    {
      "Piping Class": "91432",
      "Size": "3",
      "SCH": "160",
      "Wall thickness": "11.1252",
      "Material_Name": "ASTM A106-B",
      "PMSMat_Categories": "Carbon steel",
      "PMSMat_Cat": "CS",
      "Rating": "900",
      "Corrosion": "3",
      "convertedBore": 80,
      "_sourceRowIndex": 9775
    },
    {
      "Piping Class": "91432",
      "Size": "4",
      "SCH": "120",
      "Wall thickness": "11.1252",
      "Material_Name": "ASTM A106-B",
      "PMSMat_Categories": "Carbon steel",
      "PMSMat_Cat": "CS",
      "Rating": "900",
      "Corrosion": "3",
      "convertedBore": 100,
      "_sourceRowIndex": 9776
    },
    {
      "Piping Class": "91432",
      "Size": "6",
      "SCH": "120",
      "Wall thickness": "14.274800000000001",
      "Material_Name": "ASTM A106-B",
      "PMSMat_Categories": "Carbon steel",
      "PMSMat_Cat": "CS",
      "Rating": "900",
      "Corrosion": "3",
      "convertedBore": 150,
      "_sourceRowIndex": 9777
    },
    {
      "Piping Class": "91432",
      "Size": "8",
      "SCH": "120",
      "Wall thickness": "18.262599999999999",
      "Material_Name": "ASTM A106-B",
      "PMSMat_Categories": "Carbon steel",
      "PMSMat_Cat": "CS",
      "Rating": "900",
      "Corrosion": "3",
      "convertedBore": 200,
      "_sourceRowIndex": 9778
    },
    {
      "Piping Class": "91432",
      "Size": "10",
      "SCH": "120",
      "Wall thickness": "21.4376",
      "Material_Name": "ASTM A106-B",
      "PMSMat_Categories": "Carbon steel",
      "PMSMat_Cat": "CS",
      "Rating": "900",
      "Corrosion": "3",
      "convertedBore": 250,
      "_sourceRowIndex": 9779
    },
    {
      "Piping Class": "91432",
      "Size": "12",
      "SCH": "120",
      "Wall thickness": "25.4",
      "Material_Name": "ASTM A333-6",
      "PMSMat_Categories": "Carbon steel",
      "PMSMat_Cat": "CS",
      "Rating": "900",
      "Corrosion": "3",
      "convertedBore": 300,
      "_sourceRowIndex": 9780
    },
    {
      "Piping Class": "91432",
      "Size": "14",
      "SCH": "120",
      "Wall thickness": "27.787600000000001",
      "Material_Name": "ASTM A333-6",
      "PMSMat_Categories": "Carbon steel",
      "PMSMat_Cat": "CS",
      "Rating": "900",
      "Corrosion": "3",
      "convertedBore": 350,
      "_sourceRowIndex": 9781
    },
    {
      "Piping Class": "91432",
      "Size": "16",
      "SCH": "120",
      "Wall thickness": "30.962599999999998",
      "Material_Name": "ASTM A333-6",
      "PMSMat_Categories": "Carbon steel",
      "PMSMat_Cat": "CS",
      "Rating": "900",
      "Corrosion": "3",
      "convertedBore": 400,
      "_sourceRowIndex": 9782
    },
    {
      "Piping Class": "91432",
      "Size": "18",
      "SCH": "120",
      "Wall thickness": "34.924999999999997",
      "Material_Name": "ASTM A333-6",
      "PMSMat_Categories": "Carbon steel",
      "PMSMat_Cat": "CS",
      "Rating": "900",
      "Corrosion": "3",
      "convertedBore": 450,
      "_sourceRowIndex": 9783
    },
    {
      "Piping Class": "91432",
      "Size": "20",
      "SCH": "120",
      "Wall thickness": "38.1",
      "Material_Name": "ASTM A333-6",
      "PMSMat_Categories": "Carbon steel",
      "PMSMat_Cat": "CS",
      "Rating": "900",
      "Corrosion": "3",
      "convertedBore": 500,
      "_sourceRowIndex": 9784
    },
    {
      "Piping Class": "91432",
      "Size": "24",
      "SCH": "120",
      "Wall thickness": "46.024799999999999",
      "Material_Name": "ASTM A333-6",
      "PMSMat_Categories": "Carbon steel",
      "PMSMat_Cat": "CS",
      "Rating": "900",
      "Corrosion": "3",
      "convertedBore": 600,
      "_sourceRowIndex": 9785
    }
  ]
}
